<?xml version="1.0" encoding="iso-8859-1"?>
<xdm:container xmlns:xdm="http://www.netspective.org/Framework/Commons/XMLDataModel">
	<xdm:include file="templates/person.xml"/>
	
	<dialogs package="person">	
		<dialog type="schema-record-editor" name="nurse">
            <frame heading="create-dialog-perspective-heading:Nursing Staff"/>
			<xdm:include template="person.personal-profile"/>
			<xdm:include template="non-patient.demographic-information"/>
			<xdm:include template="person.identification-information"/>
			<xdm:include template="person.contact-information"/>
			<xdm:include template="person.employment-information"/>

			<xdm:include template="staff.professional-identification"/>
			<xdm:include template="staff.speciality"/>
			
			<xdm:include template="nurse.associated-physicians"/>
            <!--listener class="app.form.person.NurseDialog" /-->
            <on-add-data>
                <person _auto-map="*" rec_stat_id="static:Active">
                    <person-contact rec-stat-id="static:Active" method-type="static:Telephone: Business" method-value="work_phone"
                        _condition="vc.getFieldStates().getState('work_phone').getValue().hasValue()"/>
                    <person-contact rec-stat-id="static:Active" method-type="static:Email: Business" method-value="email"
                         _condition="vc.getFieldStates().getState('email').getValue().hasValue()"/>
                    <person-login user_id="user_id" password="field:password1" rec-stat-id="static:Active"
                        quantity="static:100"/>
                </person>
            </on-add-data>
            <on-delete-data>
                <person _pk-value="request:person_id" _auto-map="*" />
            </on-delete-data>
		</dialog>

		<dialog type="schema-record-editor" name="patient">
            <frame heading="create-dialog-perspective-heading:Patient/Person"/>
			<xdm:include template="person.personal-profile"/>
			<xdm:include template="patient.demographic-information"/>
			<xdm:include template="person.identification-information"/>
			<xdm:include template="person.contact-information"/>
			<xdm:include template="person.employment-information"/>
			<xdm:include template="person.insurance-information"/>
            <!--listener class="app.form.person.PatientDialog" /-->
		</dialog>

		<!--dialog type="schema-record-editor" name="person">
            <frame heading="create-dialog-perspective-heading:Person"/>
			<xdm:include template="person.personal-profile"/>
			<xdm:include template="person.demographic-information"/>
		</dialog-->

		<dialog type="schema-record-editor" name="physician">
            <frame heading="create-dialog-perspective-heading:Physician/Provider"/>
			<xdm:include template="person.personal-profile"/>
			<xdm:include template="non-patient.demographic-information"/>
			<xdm:include template="person.identification-information"/>
			<xdm:include template="person.contact-information"/>
			<xdm:include template="person.employment-information"/>
			
			<xdm:include template="staff.professional-identification"/>
			<xdm:include template="staff.speciality"/>
			
			<xdm:include template="physician.license-and-provider-information"/>
			<xdm:include template="physician.billing-information"/>
            <!--listener class="app.form.person.PhysicianDialog" /-->
		</dialog>
		
		<dialog type="schema-record-editor" name="referringDoctor">
            <frame heading="create-dialog-perspective-heading:Referring Doctor"/>
			<xdm:include template="person.personal-profile"/>
			<xdm:include template="non-patient.demographic-information"/>
			<xdm:include template="person.identification-information"/>
			<xdm:include template="person.contact-information"/>
			<xdm:include template="person.employment-information"/>

			<xdm:include template="staff.professional-identification"/>
			<xdm:include template="staff.speciality"/>

			<xdm:include template="physician.license-and-provider-information"/>
            <!--listener class="app.form.person.ReferringDoctorDialog" /-->
		</dialog>

		<dialog type="schema-record-editor" name="staff">
            <frame heading="create-dialog-perspective-heading:Staff"/>
			<xdm:include template="person.personal-profile"/>
			<xdm:include template="non-patient.demographic-information"/>
			<xdm:include template="person.identification-information"/>
			<xdm:include template="person.contact-information"/>
			<xdm:include template="person.employment-information"/>

			<xdm:include template="staff.professional-identification"/>
            <!--listener class="app.form.person.StaffDialog" /-->
		</dialog>
	</dialogs>
</xdm:container>
